setup.py
sxrobot/test.py
sxrobot/webserver.py
sxrobot/wxbot.py
sxrobot.egg-info/PKG-INFO
sxrobot.egg-info/SOURCES.txt
sxrobot.egg-info/dependency_links.txt
sxrobot.egg-info/top_level.txt