Metadata-Version: 1.1
Name: sxrobot
Version: 1.0.0.dev1
Summary: A wechat robot
Home-page: https://git.oschina.net/suxiaonao/sxrobot.git
Author: suxiaonao
Author-email: scathy1990@sina.com
License: Mozilla Public License 2.0 (MPL 2.0)
Keywords: sxrobot
Platform: UNKNOWN
Classifier: Development Status :: 1 - Planning
Classifier: Intended Audience :: Developers
Classifier: Topic :: Communications :: Chat
Classifier: License :: OSI Approved :: Mozilla Public License 2.0 (MPL 2.0)
Classifier: Programming Language :: Python :: 2.6
Classifier: Programming Language :: Python :: 2.7
Classifier: Programming Language :: Python :: 3
Classifier: Programming Language :: Python :: 3.3
Classifier: Programming Language :: Python :: 3.4
Classifier: Programming Language :: Python :: 3.5
